covirus/data/README.md
covirus/data/__init__.py
covirus/data/dataset.py
covirus/data/load_data.py
covirus/data/countries/exceptions.py
covirus/data/countries/load_countries_data.py
covirus/data/countries/brazil/br_dataset.py
covirus/data/countries/brazil/load_br.py
covirus/data/countries/brazil/sources/wcota.py
covirus/data/utils/__init__.py
covirus/data/utils/io/git.py
covirus/data/utils/io/storage_handlers.py
covirus/data/worldwide/load_world_data.py
covirus/data/worldwide/world_dataset.py
covirus/data/worldwide/sources/cbc_news.py
covirus/data/worldwide/sources/johns_hopkins.py
covirus/data/worldwide/sources/data/news.csv
covirus/models/plotable.py
covirus/models/compartment/SEIR.py
covirus/models/compartment/SIR.py
covirus/models/compartment/__init__.py
covirus/models/compartment/compartment.py
covirus/tests/datasets/conftest.py
covirus/tests/datasets/test_dataset_functions.py
covirus/tests/datasets/countries/test_load_countries_dataset.py
covirus/tests/datasets/world/test_load_johns_hopkins_dataset.py
covirus/tests/datasets/world/test_news_dataset.py
covirus/tests/models/utils.py
covirus/tests/models/compartment/test_seir.py
covirus/tests/models/compartment/test_sir.py
covirus-0.0.48.dist-info/AUTHORS
covirus-0.0.48.dist-info/LICENSE
covirus-0.0.48.dist-info/METADATA
covirus-0.0.48.dist-info/WHEEL
covirus-0.0.48.dist-info/pbr.json
covirus-0.0.48.dist-info/top_level.txt
covirus-0.0.48.dist-info/RECORD
